{
    "key": "group_67acf20d00135",
    "title": "Information",
    "fields": [
        {
            "key": "field_67acf20dd2ded",
            "label": "Logo footer",
            "name": "footer_logo",
            "aria-label": "",
            "type": "image",
            "instructions": "",
            "required": 1,
            "conditional_logic": 0,
            "wrapper": {
                "width": "",
                "class": "",
                "id": ""
            },
            "return_format": "array",
            "library": "all",
            "min_width": "",
            "min_height": "",
            "min_size": "",
            "max_width": "",
            "max_height": "",
            "max_size": "",
            "mime_types": "",
            "allow_in_bindings": 0,
            "preview_size": "medium"
        },
        {
            "key": "field_67acf4e1bcc3e",
            "label": "Logo header",
            "name": "header_logo",
            "aria-label": "",
            "type": "image",
            "instructions": "",
            "required": 1,
            "conditional_logic": 0,
            "wrapper": {
                "width": "",
                "class": "",
                "id": ""
            },
            "return_format": "array",
            "library": "all",
            "min_width": "",
            "min_height": "",
            "min_size": "",
            "max_width": "",
            "max_height": "",
            "max_size": "",
            "mime_types": "",
            "allow_in_bindings": 1,
            "preview_size": "medium"
        },
        {
            "key": "field_67acfe270e46a",
            "label": "Infolettre",
            "name": "infolettre",
            "aria-label": "",
            "type": "group",
            "instructions": "",
            "required": 0,
            "conditional_logic": 0,
            "wrapper": {
                "width": "",
                "class": "",
                "id": ""
            },
            "layout": "block",
            "sub_fields": [
                {
                    "key": "field_67acfe3b0e46b",
                    "label": "Libellé du bouton",
                    "name": "label",
                    "aria-label": "",
                    "type": "text",
                    "instructions": "",
                    "required": 0,
                    "conditional_logic": 0,
                    "wrapper": {
                        "width": "",
                        "class": "",
                        "id": ""
                    },
                    "default_value": "je m'inscrit",
                    "maxlength": "",
                    "allow_in_bindings": 0,
                    "placeholder": "",
                    "prepend": "",
                    "append": ""
                },
                {
                    "key": "field_67acfe500e46c",
                    "label": "Lien vers l'infolettre",
                    "name": "link",
                    "aria-label": "",
                    "type": "url",
                    "instructions": "",
                    "required": 0,
                    "conditional_logic": 0,
                    "wrapper": {
                        "width": "",
                        "class": "",
                        "id": ""
                    },
                    "default_value": "",
                    "allow_in_bindings": 0,
                    "placeholder": ""
                },
                {
                    "key": "field_67ad03739009d",
                    "label": "Text de l'infolettre",
                    "name": "text",
                    "aria-label": "",
                    "type": "text",
                    "instructions": "",
                    "required": 0,
                    "conditional_logic": 0,
                    "wrapper": {
                        "width": "",
                        "class": "",
                        "id": ""
                    },
                    "default_value": "Inscrivez-vous à notre infolettre pour recevoir les dernières nouvelles.",
                    "maxlength": "",
                    "allow_in_bindings": 0,
                    "placeholder": "",
                    "prepend": "",
                    "append": ""
                }
            ]
        }
    ],
    "location": [
        [
            {
                "param": "post_type",
                "operator": "==",
                "value": "info"
            }
        ]
    ],
    "menu_order": 0,
    "position": "normal",
    "style": "default",
    "label_placement": "top",
    "instruction_placement": "label",
    "hide_on_screen": "",
    "active": true,
    "description": "",
    "show_in_rest": 0,
    "modified": 1739392255
}
